agrirouter/__init__.py
agrirouter/auth/__init__.py
agrirouter/auth/auth.py
agrirouter/auth/dto.py
agrirouter/auth/enums.py
agrirouter/auth/exceptions.py
agrirouter/auth/parameters.py
agrirouter/auth/response.py
agrirouter/constants/__init__.py
agrirouter/constants/media_types.py
agrirouter/environments/__init__.py
agrirouter/environments/environmental_services.py
agrirouter/environments/environments.py
agrirouter/environments/exceptions.py
agrirouter/environments/keys.py
agrirouter/generated/__init__.py
agrirouter/generated/cloud_provider_integration/__init__.py
agrirouter/generated/cloud_provider_integration/cloud_virtualized_app_registration_pb2.py
agrirouter/generated/commons/__init__.py
agrirouter/generated/commons/chunk_pb2.py
agrirouter/generated/commons/message_pb2.py
agrirouter/generated/messaging/__init__.py
agrirouter/generated/messaging/request/__init__.py
agrirouter/generated/messaging/request/request_pb2.py
agrirouter/generated/messaging/request/payload/__init__.py
agrirouter/generated/messaging/request/payload/account/__init__.py
agrirouter/generated/messaging/request/payload/account/endpoints_pb2.py
agrirouter/generated/messaging/request/payload/efdi/__init__.py
agrirouter/generated/messaging/request/payload/efdi/efdi_pb2.py
agrirouter/generated/messaging/request/payload/endpoint/__init__.py
agrirouter/generated/messaging/request/payload/endpoint/capabilities_pb2.py
agrirouter/generated/messaging/request/payload/endpoint/subscription_pb2.py
agrirouter/generated/messaging/request/payload/feed/__init__.py
agrirouter/generated/messaging/request/payload/feed/feed_requests_pb2.py
agrirouter/generated/messaging/request/payload/gps/__init__.py
agrirouter/generated/messaging/request/payload/gps/gps_pb2.py
agrirouter/generated/messaging/response/__init__.py
agrirouter/generated/messaging/response/response_pb2.py
agrirouter/generated/messaging/response/payload/__init__.py
agrirouter/generated/messaging/response/payload/account/__init__.py
roj_agrirouter_sdk_python-1.0.8.dist-info/LICENSE
roj_agrirouter_sdk_python-1.0.8.dist-info/METADATA
roj_agrirouter_sdk_python-1.0.8.dist-info/WHEEL
roj_agrirouter_sdk_python-1.0.8.dist-info/top_level.txt
roj_agrirouter_sdk_python-1.0.8.dist-info/RECORD
